odoo/addons/hr_holidays_notify_extra/__init__.py
odoo/addons/hr_holidays_notify_extra/__manifest__.py
odoo/addons/hr_holidays_notify_extra/i18n/ca_ES.po
odoo/addons/hr_holidays_notify_extra/i18n/es.po
odoo/addons/hr_holidays_notify_extra/models/__init__.py
odoo/addons/hr_holidays_notify_extra/models/hr_leave.py
odoo/addons/hr_holidays_notify_extra/models/hr_leave_type.py
odoo/addons/hr_holidays_notify_extra/tests/__init__.py
odoo/addons/hr_holidays_notify_extra/tests/test_hr_holiday_notify_extra.py
odoo/addons/hr_holidays_notify_extra/views/hr_leave_type.xml
odoo12_addon_hr_holidays_notify_extra-12.0.1.0.2.dist-info/METADATA
odoo12_addon_hr_holidays_notify_extra-12.0.1.0.2.dist-info/WHEEL
odoo12_addon_hr_holidays_notify_extra-12.0.1.0.2.dist-info/top_level.txt
odoo12_addon_hr_holidays_notify_extra-12.0.1.0.2.dist-info/RECORD
