Metadata-Version: 2.1
Name: odoo12-addon-hr-holidays-notify-extra
Version: 12.0.1.0.2
Summary: Notify other employees by mail on Leave Requests creation depending on the type
Home-page: https://gitlab.com/coopdevs/odoo-addons
Author: César López Ramírez (Coopdevs Treball SCCL)
License: AGPL-3
Platform: UNKNOWN
Classifier: Programming Language :: Python
Classifier: Framework :: Odoo
Classifier: License :: OSI Approved :: GNU Affero General Public License v3
Requires-Python: >=3.5
Requires-Dist: odoo12-addon-hr-employee-multidepartment (==12.0.0.0.5)
Requires-Dist: odoo (<12.1dev,>=12.0a)
